smart_tests/__init__.py
smart_tests/__main__.py
smart_tests/app.py
smart_tests/testpath.py
smart_tests/version.py
smart_tests/args4p/README.md
smart_tests/args4p/__init__.py
smart_tests/args4p/argument.py
smart_tests/args4p/command.py
smart_tests/args4p/decorators.py
smart_tests/args4p/exceptions.py
smart_tests/args4p/option.py
smart_tests/args4p/parameter.py
smart_tests/args4p/converters/__init__.py
smart_tests/args4p/typer/__init__.py
smart_tests/commands/__init__.py
smart_tests/commands/detect_flakes.py
smart_tests/commands/subset.py
smart_tests/commands/test_path_writer.py
smart_tests/commands/verify.py
smart_tests/commands/compare/__init__.py
smart_tests/commands/compare/subsets.py
smart_tests/commands/inspect/__init__.py
smart_tests/commands/inspect/model.py
smart_tests/commands/inspect/subset.py
smart_tests/commands/record/__init__.py
smart_tests/commands/record/attachment.py
smart_tests/commands/record/build.py
smart_tests/commands/record/case_event.py
smart_tests/commands/record/commit.py
smart_tests/commands/record/session.py
smart_tests/commands/record/tests.py
smart_tests/commands/stats/__init__.py
smart_tests/commands/stats/test_sessions.py
smart_tests/jar/exe_deploy.jar
smart_tests/plugins/__init__.py
smart_tests/test_runners/__init__.py
smart_tests/test_runners/adb.py
smart_tests/test_runners/ant.py
smart_tests/test_runners/bazel.py
smart_tests/test_runners/behave.py
smart_tests/test_runners/codeceptjs.py
smart_tests/test_runners/ctest.py
smart_tests/test_runners/cts.py
smart_tests/test_runners/cucumber.py
smart_tests/test_runners/cypress.py
smart_tests/test_runners/dotnet.py
smart_tests/test_runners/file.py
smart_tests/test_runners/flutter.py
smart_tests/test_runners/go_test.py
smart_tests/test_runners/googletest.py
smart_tests/test_runners/gradle.py
smart_tests/test_runners/jasmine.py
smart_tests/test_runners/jest.py
smart_tests/test_runners/karma.py
smart_tests/test_runners/maven.py
smart_tests/test_runners/minitest.py
smart_tests_cli-2.3.0.dist-info/licenses/LICENSE.txt
smart_tests_cli-2.3.0.dist-info/METADATA
smart_tests_cli-2.3.0.dist-info/WHEEL
smart_tests_cli-2.3.0.dist-info/entry_points.txt
smart_tests_cli-2.3.0.dist-info/top_level.txt
smart_tests_cli-2.3.0.dist-info/RECORD
