Metadata-Version: 2.4
Name: smart-tests-cli
Version: 2.3.0
Summary: Smart Tests CLI
Author-email: CloudBees <support@cloudbees.com>
License: Apache Software License v2
Project-URL: Homepage, https://www.cloudbees.com/capabilities/cloudbees-smart-tests
Project-URL: Repository, https://github.com/launchableinc/cli
Classifier: Programming Language :: Python :: 3
Classifier: License :: OSI Approved :: Apache Software License
Classifier: Operating System :: OS Independent
Requires-Python: >=3.13
License-File: LICENSE.txt
Requires-Dist: requests>=2.32.5
Requires-Dist: urllib3>=2.5
Requires-Dist: junitparser>=4.0.0
Requires-Dist: more-itertools>=7.1.0
Requires-Dist: python-dateutil>=2.9
Requires-Dist: tabulate>=0.9
Requires-Dist: click<8.2,>=8.1
Dynamic: license-file
